tempdb/__init__.py
tempdb/_compat.py
tempdb/discover.py
tempdb/postgres.py
tempdb/utils.py
tempdb-0.1.0.dist-info/LICENSE
tempdb-0.1.0.dist-info/METADATA
tempdb-0.1.0.dist-info/WHEEL
tempdb-0.1.0.dist-info/top_level.txt
tempdb-0.1.0.dist-info/RECORD
