Metadata-Version: 2.1
Name: tempdb
Version: 0.1.0
Summary: Create temporary databases for testing.
Home-page: https://github.com/runfalk/tempdb
Author: Andreas Runfalk
Author-email: andreas@runfalk.se
License: MIT
Platform: UNKNOWN
Classifier: Programming Language :: Python
Classifier: Programming Language :: Python :: 2.7
Classifier: Programming Language :: Python :: 3.4
Classifier: Programming Language :: Python :: 3.5
Classifier: Programming Language :: Python :: 3.6
Classifier: Programming Language :: Python :: 3.7
Classifier: Topic :: Database
Classifier: Topic :: Software Development :: Libraries :: Python Modules
Classifier: Topic :: Software Development :: Testing
Classifier: Topic :: Software Development :: Testing :: Unit
Requires-Dist: psycopg2-binary (>=2.5)
Provides-Extra: dev
Requires-Dist: pytest (>=3) ; extra == 'dev'
